mpfsim/__init__.py
mpfsim/core/__init__.py
mpfsim/core/constants.py
mpfsim/core/fetch_tools.py
mpfsim/core/tool.py
mpfsim/core/tool_class.py
mpfsim/core/tool_expert.py
mpfsim/core/tool_parallel.py
mpfsim/core/tool_sql.py
mpfsim/mechanism/__init__.py
mpfsim/mechanism/data_control/__init__.py
mpfsim/mechanism/data_control/well_data_entry.py
mpfsim/mechanism/ipr_model/__init__.py
mpfsim/mechanism/ipr_model/ipr_model.py
mpfsim/mechanism/pressure_calc/__init__.py
mpfsim/mechanism/pressure_calc/pressure_gradient_method.py
mpfsim/mechanism/pressure_calc/pressure_gradient_method_only_pressure.py
mpfsim/mechanism/pressure_calc/pressure_tools.py
mpfsim/mechanism/pressure_calc/presure_iteration.py
mpfsim/mechanism/property/__init__.py
mpfsim/mechanism/property/black_oil.py
mpfsim/mechanism/property/black_oil_tools.py
mpfsim/mechanism/property/compositional_tools.py
mpfsim/mechanism/property/manage_properties.py
mpfsim/mechanism/temperature_calc/__init__.py
mpfsim/mechanism/temperature_calc/temperature_gradient_method.py
mpfsim/mechanism/temperature_calc/temperature_tools.py
mpfsim/mechanism/unit_conversion/__init__.py
mpfsim/mechanism/unit_conversion/unit_conversion.py
mpfsim/optimize/__init__.py
mpfsim/optimize/algorithm.py
mpfsim/test/__init__.py
mpfsim/test/q.py
mpfsim/test/sql.py
mpfsim/test/test_presure_iteration.py
mpfsim-1.0.3.dist-info/LICENSE
mpfsim-1.0.3.dist-info/METADATA
mpfsim-1.0.3.dist-info/WHEEL
mpfsim-1.0.3.dist-info/top_level.txt
mpfsim-1.0.3.dist-info/RECORD
