Metadata-Version: 2.1
Name: mpfsim
Version: 1.0.3
Summary: Multiphase Simulation
Home-page: https://gitee.com/mmmahhhhe/mpfsim
Author: He Ma
Author-email: mahepetroleum@163.com
Keywords: multiphase simulation,pipesim
Classifier: Programming Language :: Python :: 3
Classifier: License :: OSI Approved :: MIT License
Classifier: Operating System :: OS Independent
License-File: LICENSE
